yt_manager/__init__.py
yt_manager/core.py
yt_manager/core_async.py
yt_manager/core_sync.py
yt_manager-0.1.0.dist-info/LICENSE
yt_manager-0.1.0.dist-info/METADATA
yt_manager-0.1.0.dist-info/WHEEL
yt_manager-0.1.0.dist-info/top_level.txt
yt_manager-0.1.0.dist-info/RECORD
